odoo/addons/stock_barcodes_elaboration/README.rst
odoo/addons/stock_barcodes_elaboration/__init__.py
odoo/addons/stock_barcodes_elaboration/__manifest__.py
odoo/addons/stock_barcodes_elaboration/i18n/stock_barcodes_elaboration.pot
odoo/addons/stock_barcodes_elaboration/readme/CONTRIBUTORS.rst
odoo/addons/stock_barcodes_elaboration/readme/DESCRIPTION.rst
odoo/addons/stock_barcodes_elaboration/readme/USAGE.rst
odoo/addons/stock_barcodes_elaboration/static/description/icon.png
odoo/addons/stock_barcodes_elaboration/static/description/index.html
odoo/addons/stock_barcodes_elaboration/static/src/css/stock_barcodes_elaboration.scss
odoo/addons/stock_barcodes_elaboration/wizard/__init__.py
odoo/addons/stock_barcodes_elaboration/wizard/stock_barcodes_read_picking.py
odoo/addons/stock_barcodes_elaboration/wizard/stock_barcodes_read_picking_views.xml
odoo/addons/stock_barcodes_elaboration/wizard/stock_barcodes_read_todo.py
odoo/addons/stock_barcodes_elaboration/wizard/stock_barcodes_read_todo_view.xml
odoo_addon_stock_barcodes_elaboration-15.0.1.1.1.dist-info/METADATA
odoo_addon_stock_barcodes_elaboration-15.0.1.1.1.dist-info/WHEEL
odoo_addon_stock_barcodes_elaboration-15.0.1.1.1.dist-info/top_level.txt
odoo_addon_stock_barcodes_elaboration-15.0.1.1.1.dist-info/RECORD
